pirupy/__init__.py
pirupy/piru.py
pirupy_by_sporniket-0.0.3.dist-info/LICENSE
pirupy_by_sporniket-0.0.3.dist-info/METADATA
pirupy_by_sporniket-0.0.3.dist-info/WHEEL
pirupy_by_sporniket-0.0.3.dist-info/top_level.txt
pirupy_by_sporniket-0.0.3.dist-info/RECORD
