Metadata-Version: 2.1
Name: pirupy-by-sporniket
Version: 0.0.3
Summary: PIRUPY, a PIpeline RUnner for PYthon
Home-page: https://github.com/sporniket/pirupy
Author: Sporniket
Author-email: sporniket.studio@gmail.com
License: UNKNOWN
Project-URL: Bug Tracker, https://github.com/sporniket/pirupy/issues
Platform: UNKNOWN
Classifier: Programming Language :: Python :: 3
Classifier: License :: OSI Approved :: GNU Lesser General Public License v3 or later (LGPLv3+)
Classifier: Operating System :: OS Independent
Classifier: Development Status :: 3 - Alpha
Classifier: Environment :: Console
Requires-Python: >=3.6
License-File: LICENSE
